LICENSE.md
monkeyble/__init__.py
monkeyble/_version.py
monkeyble/cli/__init__.py
monkeyble/cli/const.py
monkeyble/cli/exceptions.py
monkeyble/cli/models.py
monkeyble/cli/monkeyble.yml
monkeyble/cli/monkeyble_cli.py
monkeyble/cli/utils.py
monkeyble-1.4.0.dist-info/LICENSE.md
monkeyble-1.4.0.dist-info/METADATA
monkeyble-1.4.0.dist-info/WHEEL
monkeyble-1.4.0.dist-info/entry_points.txt
monkeyble-1.4.0.dist-info/RECORD
